<mapreducescript scriptid="customscript_nse_mr_csv_import">
  <description></description>
  <isinactive>F</isinactive>
  <name>NSE MR CSV Import</name>
  <notifyadmins>F</notifyadmins>
  <notifyemails></notifyemails>
  <notifyowner>T</notifyowner>
  <scriptfile>[/SuiteScripts/CSV Import/nse_sd_mr_csv_import.js]</scriptfile>
  <scriptcustomfields>
    <scriptcustomfield scriptid="custscript_nse_mr_csv_import_fileid">
      <accesslevel>2</accesslevel>
      <applyformatting>T</applyformatting>
      <checkspelling>F</checkspelling>
      <defaultchecked>F</defaultchecked>
      <defaultselection></defaultselection>
      <defaultvalue></defaultvalue>
      <description></description>
      <displayheight></displayheight>
      <displaytype>NORMAL</displaytype>
      <displaywidth></displaywidth>
      <dynamicdefault></dynamicdefault>
      <fieldtype>INTEGER</fieldtype>
      <help></help>
      <isformula>F</isformula>
      <ismandatory>F</ismandatory>
      <label>File ID</label>
      <linktext></linktext>
      <maxlength></maxlength>
      <maxvalue></maxvalue>
      <minvalue></minvalue>
      <onparentdelete></onparentdelete>
      <searchlevel>2</searchlevel>
      <selectrecordtype></selectrecordtype>
      <setting></setting>
      <storevalue>T</storevalue>
    </scriptcustomfield>
    <scriptcustomfield scriptid="custscript_nse_mr_csv_import_map">
      <accesslevel>2</accesslevel>
      <applyformatting>F</applyformatting>
      <checkspelling>F</checkspelling>
      <defaultchecked>F</defaultchecked>
      <defaultselection></defaultselection>
      <defaultvalue></defaultvalue>
      <description></description>
      <displayheight></displayheight>
      <displaytype>NORMAL</displaytype>
      <displaywidth></displaywidth>
      <dynamicdefault></dynamicdefault>
      <fieldtype>CLOBTEXT</fieldtype>
      <help></help>
      <isformula>F</isformula>
      <ismandatory>F</ismandatory>
      <label>Mapping</label>
      <linktext></linktext>
      <maxlength></maxlength>
      <maxvalue></maxvalue>
      <minvalue></minvalue>
      <onparentdelete></onparentdelete>
      <searchlevel>2</searchlevel>
      <selectrecordtype></selectrecordtype>
      <setting></setting>
      <storevalue>T</storevalue>
    </scriptcustomfield>
    <scriptcustomfield scriptid="custscript_nse_mr_csv_import_option">
      <accesslevel>2</accesslevel>
      <applyformatting>F</applyformatting>
      <checkspelling>F</checkspelling>
      <defaultchecked>F</defaultchecked>
      <defaultselection></defaultselection>
      <defaultvalue></defaultvalue>
      <description></description>
      <displayheight></displayheight>
      <displaytype>NORMAL</displaytype>
      <displaywidth></displaywidth>
      <dynamicdefault></dynamicdefault>
      <fieldtype>CLOBTEXT</fieldtype>
      <help></help>
      <isformula>F</isformula>
      <ismandatory>F</ismandatory>
      <label>Options</label>
      <linktext></linktext>
      <maxlength></maxlength>
      <maxvalue></maxvalue>
      <minvalue></minvalue>
      <onparentdelete></onparentdelete>
      <searchlevel>2</searchlevel>
      <selectrecordtype></selectrecordtype>
      <setting></setting>
      <storevalue>T</storevalue>
    </scriptcustomfield>
    <scriptcustomfield scriptid="custscript_nse_mr_csv_import_user">
      <accesslevel>2</accesslevel>
      <applyformatting>F</applyformatting>
      <checkspelling>F</checkspelling>
      <defaultchecked>F</defaultchecked>
      <defaultselection></defaultselection>
      <defaultvalue></defaultvalue>
      <description></description>
      <displayheight></displayheight>
      <displaytype>NORMAL</displaytype>
      <displaywidth></displaywidth>
      <dynamicdefault></dynamicdefault>
      <fieldtype>SELECT</fieldtype>
      <help></help>
      <isformula>F</isformula>
      <ismandatory>F</ismandatory>
      <label>User</label>
      <linktext></linktext>
      <maxlength></maxlength>
      <maxvalue></maxvalue>
      <minvalue></minvalue>
      <onparentdelete>SET_NULL</onparentdelete>
      <searchlevel>2</searchlevel>
      <selectrecordtype>-4</selectrecordtype>
      <setting></setting>
      <storevalue>T</storevalue>
    </scriptcustomfield>
    <scriptcustomfield scriptid="custscript_nse_mr_csv_import_sub">
      <accesslevel>2</accesslevel>
      <applyformatting>F</applyformatting>
      <checkspelling>F</checkspelling>
      <defaultchecked>F</defaultchecked>
      <defaultselection></defaultselection>
      <defaultvalue></defaultvalue>
      <description></description>
      <displayheight></displayheight>
      <displaytype>NORMAL</displaytype>
      <displaywidth></displaywidth>
      <dynamicdefault></dynamicdefault>
      <fieldtype>SELECT</fieldtype>
      <help></help>
      <isformula>F</isformula>
      <ismandatory>F</ismandatory>
      <label>Subsidiary</label>
      <linktext></linktext>
      <maxlength></maxlength>
      <maxvalue></maxvalue>
      <minvalue></minvalue>
      <onparentdelete>NO_ACTION</onparentdelete>
      <searchlevel>2</searchlevel>
      <selectrecordtype>-117</selectrecordtype>
      <setting></setting>
      <storevalue>T</storevalue>
    </scriptcustomfield>
  </scriptcustomfields>
  <scriptdeployments>
    <scriptdeployment scriptid="customdeploy_nse_mr_csv_import">
      <buffersize>1</buffersize>
      <concurrencylimit>1</concurrencylimit>
      <custscript_nse_mr_csv_import_fileid></custscript_nse_mr_csv_import_fileid>
      <custscript_nse_mr_csv_import_map>{&quot;SrvItem&quot;:{&quot;recType&quot;:&quot;SERVICE_ITEM&quot;,&quot;defaultValues&quot;:{&quot;taxschedule&quot;:1},&quot;External ID&quot;:&quot;externalid&quot;,&quot;ID&quot;:&quot;itemid&quot;,&quot;Name&quot;:&quot;displayname&quot;,&quot;Subsidiary&quot;:&quot;subsidiary&quot;},&quot;Vendor&quot;:{&quot;recType&quot;:&quot;VENDOR&quot;,&quot;External ID&quot;:&quot;externalid&quot;,&quot;Name&quot;:&quot;companyname&quot;,&quot;Legal Name&quot;:&quot;legalname&quot;,&quot;Subsidiary&quot;:&quot;subsidiary&quot;,&quot;Email&quot;:&quot;email&quot;,&quot;lineMapping&quot;:{&quot;lineId&quot;:&quot;currency&quot;,&quot;Currency&quot;:&quot;currency&quot;}},&quot;Journal&quot;:{&quot;recType&quot;:&quot;JOURNAL_ENTRY&quot;,&quot;defaultValues&quot;:{&quot;customform&quot;:30,&quot;subsidiary&quot;:2},&quot;External ID&quot;:&quot;externalid&quot;,&quot;Currency&quot;:&quot;currency&quot;,&quot;Date&quot;:&quot;trandate&quot;,&quot;lineMapping&quot;:{&quot;lineId&quot;:&quot;line&quot;,&quot;Bank Account&quot;:&quot;account&quot;,&quot;Memo&quot;:&quot;memo&quot;,&quot;Class&quot;:&quot;class&quot;,&quot;Amount&quot;:&quot;credit&quot;}},&quot;Customer Payment&quot;:{&quot;recType&quot;:&quot;CUSTOMER_PAYMENT&quot;,&quot;Name&quot;:&quot;customer&quot;,&quot;External ID&quot;:&quot;externalid&quot;,&quot;Currency&quot;:&quot;currency&quot;,&quot;Exchange Rate&quot;:&quot;exchangerate&quot;,&quot;Bank Account&quot;:&quot;account&quot;,&quot;Date&quot;:&quot;trandate&quot;,&quot;Memo&quot;:&quot;memo&quot;,&quot;Department&quot;:&quot;department&quot;,&quot;Website&quot;:&quot;class&quot;,&quot;Location&quot;:&quot;location&quot;,&quot;Amount&quot;:&quot;payment&quot;,&quot;lineMapping&quot;:{&quot;lineId&quot;:&quot;apply&quot;,&quot;Invoice/Bill&quot;:&quot;internalid&quot;,&quot;Applying Amount&quot;:&quot;amount&quot;}}}</custscript_nse_mr_csv_import_map>
      <custscript_nse_mr_csv_import_option>{&quot;textValueFields&quot;:[&quot;customer&quot;,&quot;entity&quot;,&quot;currency&quot;,&quot;account&quot;,&quot;department&quot;,&quot;class&quot;,&quot;location&quot;],&quot;dateValueFields&quot;:[&quot;trandate&quot;],&quot;setExternalId&quot;:false,&quot;csvDelimiter&quot;:&quot;,&quot;,&quot;postToLockedPeriod&quot;:false,&quot;bodyInitialFields&quot;:[&quot;customform&quot;,&quot;entity&quot;,&quot;customer&quot;,&quot;subsidiary&quot;],&quot;lineInitialFields&quot;:[&quot;item&quot;,&quot;account&quot;],&quot;applySublists&quot;:[&quot;apply&quot;,&quot;credit&quot;,&quot;debit&quot;],&quot;permissionMap&quot;:{&quot;JOURNAL_ENTRY&quot;:&quot;TRAN_JOURNAL&quot;,&quot;CUSTOMER_PAYMENT&quot;:&quot;TRAN_CUSTPYMT&quot;,&quot;VENDOR_PAYMENT&quot;:&quot;TRAN_VENDPYMT&quot;,&quot;CUSTOMER_DEPOSIT&quot;:&quot;TRAN_CUSTDEP&quot;,&quot;CUSTOMER_REFUND&quot;:&quot;TRAN_CUSTRFND&quot;,&quot;SERVICE_ITEM&quot;:&quot;LIST_ITEM&quot;,&quot;VENDOR&quot;:&quot;LIST_VENDOR&quot;}}</custscript_nse_mr_csv_import_option>
      <custscript_nse_mr_csv_import_sub></custscript_nse_mr_csv_import_sub>
      <custscript_nse_mr_csv_import_user></custscript_nse_mr_csv_import_user>
      <isdeployed>T</isdeployed>
      <loglevel>DEBUG</loglevel>
      <queueallstagesatonce>T</queueallstagesatonce>
      <runasrole>ADMINISTRATOR</runasrole>
      <status>NOTSCHEDULED</status>
      <title>NSE MR CSV Import</title>
      <yieldaftermins>60</yieldaftermins>
      <recurrence>
        <single>
          <repeat></repeat>
          <startdate>2020-06-15</startdate>
          <starttime>16:00:00Z</starttime>
        </single>
      </recurrence>
    </scriptdeployment>
  </scriptdeployments>
</mapreducescript>